nlu/__init__.py
nlu/discovery.py
nlu/finance.py
nlu/info.py
nlu/spellbook.py
nlu/components/__init__.py
nlu/components/assertions/__init__.py
nlu/components/assertions/assertion_dl/__init__.py
nlu/components/assertions/assertion_dl/assertion_dl.py
nlu/components/assertions/assertion_log_reg/__init__.py
nlu/components/assertions/assertion_log_reg/assertion_log_reg.py
nlu/components/chunkers/__init__.py
nlu/components/chunkers/chunk_mapper/__init__.py
nlu/components/chunkers/chunk_mapper/chunk_mapper.py
nlu/components/chunkers/contextual_parser/__init__.py
nlu/components/chunkers/contextual_parser/contextual_parser.py
nlu/components/chunkers/default_chunker/__init__.py
nlu/components/chunkers/default_chunker/default_chunker.py
nlu/components/chunkers/ngram/__init__.py
nlu/components/chunkers/ngram/ngram.py
nlu/components/classifiers/__init__.py
nlu/components/classifiers/asr/__init__.py
nlu/components/classifiers/asr/wav2Vec.py
nlu/components/classifiers/asr_hubert/__init__.py
nlu/components/classifiers/asr_hubert/hubert.py
nlu/components/classifiers/classifier_dl/__init__.py
nlu/components/classifiers/classifier_dl/classifier_dl.py
nlu/components/classifiers/generic_classifier/__init__.py
nlu/components/classifiers/generic_classifier/generic_classifier.py
nlu/components/classifiers/image_classification_swin/__init__.py
nlu/components/classifiers/image_classification_swin/swin.py
nlu/components/classifiers/image_classification_vit/__init__.py
nlu/components/classifiers/image_classification_vit/convnext_image_classification.py
nlu/components/classifiers/image_classification_vit/vit_image_classifier.py
nlu/components/classifiers/language_detector/__init__.py
nlu/components/classifiers/language_detector/language_detector.py
nlu/components/classifiers/multi_classifier/__init__.py
nlu/components/classifiers/multi_classifier/multi_classifier.py
nlu/components/classifiers/named_entity_recognizer_crf/__init__.py
shailesh_bart-4.2.1.dist-info/LICENSE
shailesh_bart-4.2.1.dist-info/METADATA
shailesh_bart-4.2.1.dist-info/WHEEL
shailesh_bart-4.2.1.dist-info/top_level.txt
shailesh_bart-4.2.1.dist-info/RECORD
